minimaltrader/__init__.py
minimaltrader/brokers/__init__.py
minimaltrader/brokers/base.py
minimaltrader/brokers/simulated_broker.py
minimaltrader/core/__init__.py
minimaltrader/core/consumer.py
minimaltrader/core/event_bus.py
minimaltrader/core/producer.py
minimaltrader/datafeeds/__init__.py
minimaltrader/datafeeds/base.py
minimaltrader/datafeeds/simulated_datafeed.py
minimaltrader/desk/__init__.py
minimaltrader/desk/bookkeeper.py
minimaltrader/desk/trader.py
minimaltrader/indicators/__init__.py
minimaltrader/indicators/bar.py
minimaltrader/indicators/base.py
minimaltrader/indicators/sma.py
minimaltrader/models/__init__.py
minimaltrader/models/enums.py
minimaltrader/models/events.py
minimaltrader/models/records.py
minimaltrader/strategies/__init__.py
minimaltrader/strategies/base.py
minimaltrader/strategies/sma_crossover.py
minimaltrader/workbench.py
minimaltrader-0.10.0.dist-info/METADATA
minimaltrader-0.10.0.dist-info/WHEEL
minimaltrader-0.10.0.dist-info/licenses/LICENSE
minimaltrader-0.10.0.dist-info/RECORD
