Metadata-Version: 2.4
Name: minimaltrader
Version: 0.10.0
Summary: Minimal Trading Software
License-File: LICENSE
Author: Nils P. Kujath
Author-email: 63961429+NilsKujath@users.noreply.github.com
Requires-Python: >=3.11
Classifier: Programming Language :: Python :: 3
Classifier: Programming Language :: Python :: 3.11
Classifier: Programming Language :: Python :: 3.12
Classifier: Programming Language :: Python :: 3.13
Classifier: Programming Language :: Python :: 3.14
Requires-Dist: matplotlib (>=3.10.8,<4.0.0)
Requires-Dist: pandas (>=2.3.3,<3.0.0)
